sqlalchemy_filterset/__init__.py
sqlalchemy_filterset/constants.py
sqlalchemy_filterset/filters.py
sqlalchemy_filterset/filtersets.py
sqlalchemy_filterset/operators.py
sqlalchemy_filterset/py.typed
sqlalchemy_filterset/strategies.py
sqlalchemy_filterset/types.py
sqlalchemy_filterset-2.3.0.dist-info/LICENSE.md
sqlalchemy_filterset-2.3.0.dist-info/METADATA
sqlalchemy_filterset-2.3.0.dist-info/WHEEL
sqlalchemy_filterset-2.3.0.dist-info/RECORD
