Metadata-Version: 2.1
Name: sqlalchemy-filterset
Version: 2.3.0
Summary: An easy way to filter, sort, paginate SQLAlchemy queries
License: MIT
Author: Andrey Matveev
Author-email: ra1ze.matveev@yandex.ru
Requires-Python: >=3.7,<4.0.0
Classifier: License :: OSI Approved :: MIT License
Classifier: Programming Language :: Python :: 3
Classifier: Programming Language :: Python :: 3.7
Classifier: Programming Language :: Python :: 3.8
Classifier: Programming Language :: Python :: 3.9
Classifier: Programming Language :: Python :: 3.10
Classifier: Programming Language :: Python :: 3.11
Classifier: Programming Language :: Python :: 3.12
Requires-Dist: SQLAlchemy[asyncio] (>=2,<3)
